crawler_chrome/add.js
crawler_chrome/base_driver.py
crawler_chrome/chrome_driver.py
crawler_chrome/chrome_utils.py
crawler_chrome/chromium_driver.py
crawler_chrome/download.py
crawler_chrome/firefox_driver.py
crawler_chrome/fservice.py
crawler_chrome/phantomjs_driver.py
crawler_chrome/test_chromium.py
crawler_chrome/user_agent.py
crawler_chrome/util.py
crawler_chrome-0.0.9.dist-info/LICENSE
crawler_chrome-0.0.9.dist-info/METADATA
crawler_chrome-0.0.9.dist-info/WHEEL
crawler_chrome-0.0.9.dist-info/top_level.txt
crawler_chrome-0.0.9.dist-info/RECORD
