Metadata-Version: 2.1
Name: crawler_chrome
Version: 0.0.9
Summary: 采集工具
Author: hammer
Author-email: liuzhuogood@foxmail.com
License-File: LICENSE
